fastapi_azure_auth/__init__.py
fastapi_azure_auth/auth.py
fastapi_azure_auth/exceptions.py
fastapi_azure_auth/openid_config.py
fastapi_azure_auth/py.typed
fastapi_azure_auth/user.py
fastapi_azure_auth/utils.py
fastapi_azure_auth-5.2.0.dist-info/LICENSE
fastapi_azure_auth-5.2.0.dist-info/METADATA
fastapi_azure_auth-5.2.0.dist-info/WHEEL
fastapi_azure_auth-5.2.0.dist-info/RECORD
