Metadata-Version: 2.3
Name: fastapi-azure-auth
Version: 5.2.0
Summary: Easy and secure implementation of Azure Entra ID for your FastAPI APIs
Keywords: ad,async,asyncio,authentication,azure,azure ad,azure entra id,azure entra,entra id,azuread,fastapi,multi tenant,oauth2,oidc,security,single tenant,starlette,trio
Author: Jonas Krüger Svensson
Author-email: jonas.svensson@intility.no
Requires-Python: >=3.8,<4.0
Classifier: Development Status :: 5 - Production/Stable
Classifier: Environment :: Web Environment
Classifier: Intended Audience :: Developers
Classifier: License :: OSI Approved :: MIT License
Classifier: Operating System :: OS Independent
Classifier: Programming Language :: Python
Classifier: Programming Language :: Python :: 3
Classifier: Programming Language :: Python :: 3.8
Classifier: Programming Language :: Python :: 3.9
Classifier: Programming Language :: Python :: 3.10
Classifier: Programming Language :: Python :: 3.11
Classifier: Programming Language :: Python :: 3.12
Classifier: Programming Language :: Python :: 3.13
Classifier: Topic :: Software Development
Classifier: Topic :: Software Development :: Libraries
Classifier: Topic :: Software Development :: Libraries :: Application Frameworks
Classifier: Topic :: Software Development :: Libraries :: Python Modules
Requires-Dist: cryptography (>=43.0.1)
Requires-Dist: fastapi (>0.68.0)
Requires-Dist: httpx (>0.18.2)
Requires-Dist: pyjwt (>=2.8.0,<3.0.0)
Project-URL: Documentation, https://github.com/intility/fastapi-azure-auth
Project-URL: Homepage, https://github.com/intility/fastapi-azure-auth
Project-URL: Repository, https://github.com/intility/fastapi-azure-auth
